{"NZD/SEK": ["NZDSEK", "forex"], "NZD/USD": ["NZDUSD", "forex"], "CAD/TRY": ["CADTRY", "forex"], "EUR/CHF": ["EURCHF", "forex"], "USD/THB": ["USDTHB", "forex"], "EUR/TRY": ["EURTRY", "forex"], "GBP/AUD": ["GBPAUD", "forex"], "AUD/USD": ["AUDUSD", "forex"], "EUR/MXN": ["EURMXN", "forex"], "USD/CHF": ["USDCHF", "forex"], "NOK/DKK": ["NOKDKK", "forex"], "EUR/NOK": ["EURNOK", "forex"], "SEK/JPY": ["SEKJPY", "forex"], "CAD/NOK": ["CADNOK", "forex"], "NOK/SEK": ["NOKSEK", "forex"], "GBP/HUF": ["GBPHUF", "forex"], "GBP/SGD": ["GBPSGD", "forex"], "AUD/NZD": ["AUDNZD", "forex"], "GBP/JPY": ["GBPJPY", "forex"], "CHF/SEK": ["CHFSEK", "forex"], "AUD/NOK": ["AUDNOK", "forex"], "GBP/NOK": ["GBPNOK", "forex"], "AUD/DKK": ["AUDDKK", "forex"], "EUR/AUD": ["EURAUD", "forex"], "AUD/CHF": ["AUDCHF", "forex"], "GBP/CHF": ["GBPCHF", "forex"], "AUD/CAD": ["AUDCAD", "forex"], "CHF/DKK": ["CHFDKK", "forex"], "AUD/TRY": ["AUDTRY", "forex"], "NZD/CHF": ["NZDCHF", "forex"], "USD/SEK": ["USDSEK", "forex"], "GBP/NZD": ["GBPNZD", "forex"], "EUR/DKK": ["EURDKK", "forex"], "NZD/DKK": ["NZDDKK", "forex"], "CAD/SGD": ["CADSGD", "forex"], "EUR/GBP": ["EURGBP", "forex"], "EUR/CAD": ["EURCAD", "forex"], "USD/CZK": ["USDCZK", "forex"], "AUD/MXN": ["AUDMXN", "forex"], "EUR/NZD": ["EURNZD", "forex"], "GBP/PLN": ["GBPPLN", "forex"], "NZD/NOK": ["NZDNOK", "forex"], "AUD/SGD": ["AUDSGD", "forex"], "GBP/SEK": ["GBPSEK", "forex"], "NZD/CAD": ["NZDCAD", "forex"], "NZD/MXN": ["NZDMXN", "forex"], "NZD/TRY": ["NZDTRY", "forex"], "CHF/SGD": ["CHFSGD", "forex"], "USD/MXN": ["USDMXN", "forex"], "EUR/HUF": ["EURHUF", "forex"], "GBP/CAD": ["GBPCAD", "forex"], "USD/TRY": ["USDTRY", "forex"], "USD/JPY": ["USDJPY", "forex"], "EUR/USD": ["EURUSD", "forex"], "AUD/SEK": ["AUDSEK", "forex"], "CHF/NOK": ["CHFNOK", "forex"], "USD/PLN": ["USDPLN", "forex"], "USD/HUF": ["USDHUF", "forex"], "CHF/JPY": ["CHFJPY", "forex"], "GBP/ILS": ["GBPILS", "forex"], "NZD/JPY": ["NZDJPY", "forex"], "CHF/TRY": ["CHFTRY", "forex"], "CAD/JPY": ["CADJPY", "forex"], "USD/RUB": ["USDRUB", "forex"], "SGD/JPY": ["SGDJPY", "forex"], "GBP/USD": ["GBPUSD", "forex"], "CAD/PLN": ["CADPLN", "forex"], "DKK/SGD": ["DKKSGD", "forex"], "NZD/SGD": ["NZDSGD", "forex"], "AUD/JPY": ["AUDJPY", "forex"], "NOK/JPY": ["NOKJPY", "forex"], "PLN/SEK": ["PLNSEK", "forex"], "USD/SGD": ["USDSGD", "forex"], "GBP/MXN": ["GBPMXN", "forex"], "USD/CAD": ["USDCAD", "forex"], "SEK/DKK": ["SEKDKK", "forex"], "DKK/PLN": ["DKKPLN", "forex"], "CAD/MXN": ["CADMXN", "forex"], "GBP/TRY": ["GBPTRY", "forex"], "EUR/SGD": ["EURSGD", "forex"], "NZD/ZAR": ["NZDZAR", "forex"], "EUR/CZK": ["EURCZK", "forex"], "EUR/JPY": ["EURJPY", "forex"], "CAD/CHF": ["CADCHF", "forex"], "USD/INR": ["USDINR", "forex"], "USD/BRL": ["USDBRL", "forex"], "USD/NOK": ["USDNOK", "forex"], "USD/DKK": ["USDDKK", "forex"], "China Large-Cap ETF": ["FXI", "cfd"], "IBM Corporation": ["IBM:US", "cfd"], "IDEXX Laboratories": ["IDXX", "cfd"], "Siemens": ["SIED-CHIX", "cfd"], "Roche": ["ROGZ-CHIX", "cfd"], "Airbus SE": ["AIRP-CHIX", "cfd"], "AbbVie": ["ABBV:US", "cfd"], "Concho Resources": ["CXO:US", "cfd"], "Verizon": ["VZ:US", "cfd"], "Unilever": ["ULVRL-CHIX", "cfd"], "Lockheed Martin": ["LMT:US", "cfd"], "NextEra Energy": ["NEE:US", "cfd"], "US 100": ["USNDAQ100", "cfd"], "Entergy": ["ETR:US", "cfd"], "QQQ Trust, Series 1": ["QQQ", "cfd"], "DTE Energy": ["DTE:US", "cfd"], "Tesco": ["TSCOL-CHIX", "cfd"], "First Solar": ["FSLR:US", "cfd"], "Pfizer": ["PFE:US", "cfd"], "Eastman Chemical": ["EMN:US", "cfd"], "JP Morgan Chase": ["JPM", "cfd"], "Google": ["GOOGLE", "cfd"], "Fastenal": ["FAST:US", "cfd"], "HSBC Holdings PLC": ["HSBAL-CHIX", "cfd"], "DaVita": ["DVA:US", "cfd"], "Utilities SPDR": ["XLU", "cfd"], "Federal Realty": ["FRT:US", "cfd"], "Commerzbank": ["CBKD-CHIX", "cfd"], "Amgen": ["AMGN:US", "cfd"], "Silver": ["XAGUSD", "cfd"], "Resmed Inc": ["RMD", "cfd"], "Equifax": ["EFX:US", "cfd"], "Digital Realty Trust": ["DLR:US", "cfd"], "Adobe Systems": ["ADBE:US", "cfd"], "Autodesk": ["ADSK:US", "cfd"], "Barclays": ["BARCL-CHIX", "cfd"], "Spotify": ["SPOT", "cfd"], "Standard Chartered": ["STANL-CHIX", "cfd"], "Alibaba": ["ALIBABA", "cfd"], "Freeport-McMoRan": ["FCX:US", "cfd"], "Delta Air Lines": ["DAL:US", "cfd"], "Materials Select Sector SPDR": ["XLB", "cfd"], "Amazon": ["AMAZON", "cfd"], "Semiconductor ETF": ["SMH", "cfd"], "S&P 500 ETF": ["SPY", "cfd"], "Caterpillar": ["CAT:US", "cfd"], "US 30": ["US30", "cfd"], "ConocoPhillips": ["COP:US", "cfd"], "Flowserve": ["FLS:US", "cfd"], "Goldman Sachs": ["GS", "cfd"], "AU 200": ["AUS200", "cfd"], "Edison": ["EIX:US", "cfd"], "Crude Oil WTI": ["USOUSD", "cfd"], "MSCI Mexico ETF": ["EWW", "cfd"], "General Electric": ["GE", "cfd"], "Micron Technology": ["MU:US", "cfd"], "Telef\u00f3nica": ["TEFE-CHIX", "cfd"], "Procter & Gamble": ["PG:US", "cfd"], "Accenture": ["ACN:US", "cfd"], "Costco": ["COST:US", "cfd"], "Medtronic": ["MDT:US", "cfd"], "MSCI Emerging Markets ETF": ["EEM", "cfd"], "Expeditors": ["EXPD:US", "cfd"], "Facebook": ["FACEBOOK", "cfd"], "Tesla": ["TESLA", "cfd"], "Merck": ["MRKD-CHIX", "cfd"], "FirstEnergy": ["FE:US", "cfd"], "Altria": ["MO:US", "cfd"], "Core MSCI Emerging Markets": ["IEMG", "cfd"], "AS Roma": ["ASRM", "cfd"], "Bayer": ["BAYND-CHIX", "cfd"], "Continental": ["COND-CHIX", "cfd"], "Qualcomm": ["QCOM:US", "cfd"], "Vodafone Group PLC": ["VODL-CHIX", "cfd"], "Visa": ["V:US", "cfd"], "AT&T": ["T:US", "cfd"], "FedEx": ["FDX:US", "cfd"], "Frontier Communications": ["FTR:US", "cfd"], "Teleflex Inc": ["TFX", "cfd"], "Twitter Inc": ["TWITTER", "cfd"], "Royal Bank of Scotland": ["RBSL-CHIX", "cfd"], "S&P Oil & Gas Explor & Product": ["XOP", "cfd"], "Deutsche Post": ["DPWD-CHIX", "cfd"], "General Motors": ["GM", "cfd"], "US 500": ["USSPX500", "cfd"], "Bank of America": ["BAC:US", "cfd"], "Nike": ["NIKE", "cfd"], "Darden Restaurants": ["DRI:US", "cfd"], "UBS": ["UBSGZ-CHIX", "cfd"], "Discover Financial Services": ["DFS:US", "cfd"], "Emerson Electric": ["EMR:US", "cfd"], "Advance Auto Parts": ["AAP:US", "cfd"], "Duke Realty Corp": ["DRE", "cfd"], "Rolls-Royce": ["RRL-CHIX", "cfd"], "Wells Fargo": ["WFC:US", "cfd"], "CitiGroup": ["CITI", "cfd"], "Cisco Systems": ["CISCO", "cfd"], "Apple": ["APPLE", "cfd"], "MSCI Japan ETF": ["EWJ", "cfd"], "F5 Networks": ["FFIV:US", "cfd"], "Heinz": ["KHC:US", "cfd"], "British American Tobacco": ["BATSL-CHIX", "cfd"], "Nvidia": ["NVDA:US", "cfd"], "E.ON": ["EOAND-CHIX", "cfd"], "Citrix Systems": ["CTXS:US", "cfd"], "UK 100": ["UK100", "cfd"], "BBVA": ["BBVAE-CHIX", "cfd"], "Philip Morris Int.": ["PM:US", "cfd"], "Consolidated Edison": ["ED:US", "cfd"], "Netflix": ["NFLX:US", "cfd"], "Allianz": ["ALVD-CHIX", "cfd"], "FR 40": ["FRANCE40", "cfd"], "Schlumberger": ["SLB:US", "cfd"], "Platinum": ["XPTUSD", "cfd"], "Consumer Discretionary SPDR": ["XLY", "cfd"], "BHP Billiton": ["BLTL-CHIX", "cfd"], "Credit Suisse": ["CSGNZ-CHIX", "cfd"], "Activision Blizzard": ["ATVI:US", "cfd"], "Hasbro": ["HAS:US", "cfd"], "Bristol-Myers Squibb": ["BMY:US", "cfd"], "Equity Residential": ["EQR:US", "cfd"], "Suncor Energy Inc.": ["SU", "cfd"], "Cintas": ["CTAS:US", "cfd"], "Morgan Stanley": ["MORSTAN", "cfd"], "Devon Energy": ["DVN:US", "cfd"], "Dun & Bradstreet": ["DNB:US", "cfd"], "S&P Metals & Mining ETF": ["XME", "cfd"], "SP 35": ["SPAIN35", "cfd"], "Boeing": ["BA:US", "cfd"], "Ferrari": ["FERRARI", "cfd"], "US Real Estate ETF": ["IYR", "cfd"], "Dover": ["DOV:US", "cfd"], "Honeywell": ["HON:US", "cfd"], "Marks & Spencer": ["MKSL-CHIX", "cfd"], "BMW": ["BMWD-CHIX", "cfd"], "HK 50": ["HONGKONG50", "cfd"], "PayPal": ["PYPL:US", "cfd"], "Alcoa": ["AA:US", "cfd"], "CVS Health": ["CVS:US", "cfd"], "iShares Russell 2000 ETF": ["IWM", "cfd"], "Walgreens Boots All.": ["WBA:US", "cfd"], "ANSYS": ["ANSS", "cfd"], "Energy SPDR": ["XLE", "cfd"], "Wheat": ["W1", "cfd"], "Ecolab": ["ECL:US", "cfd"], "Starbucks": ["SBUX:US", "cfd"], "Heineken Holding NV": ["HEIOA-CHIX", "cfd"], "Quest Diagnostics": ["DGX:US", "cfd"], "easyJet": ["EZJL-CHIX", "cfd"], "JP 225": ["JAPAN225", "cfd"], "AMD": ["AMD", "cfd"], "Colgate-Palmolive": ["CL:US", "cfd"], "Salesforce.com": ["CRM:US", "cfd"], "Technology SPDR": ["XLK", "cfd"], "Dropbox": ["DBX", "cfd"], "Fidelity National Information Services": ["FIS:US", "cfd"], "3M Company": ["MMM:US", "cfd"], "Daimler": ["DAID-CHIX", "cfd"], "Baidu": ["BAIDU", "cfd"], "Wal-Mart Stores": ["WMT:US", "cfd"], "Exxon Mobil": ["XOM:US", "cfd"], "Raytheon": ["RTN:US", "cfd"], "eBay": ["EBAY:US", "cfd"], "Discovery \u2013 Class A": ["DISCA:US", "cfd"], "Oil Services ETF": ["OIH", "cfd"], "Microsoft": ["MSFT", "cfd"], "Chevron": ["CVX:US", "cfd"], "Lloyds Banking Group PLC": ["LLOYL-CHIX", "cfd"], "20+ Year Treasury Bond ETF": ["TLT", "cfd"], "Adidas": ["ADSD-CHIX", "cfd"], "Comcast \u2013 Class A": ["CMCSA:US", "cfd"], "Danaher": ["DHR:US", "cfd"], "Align Technology": ["ALGN", "cfd"], "Volkswagen": ["VOW3D-CHIX", "cfd"], "Fiserv": ["FISV:US", "cfd"], "L'Oreal": ["ORP-CHIX", "cfd"], "D. R. Horton": ["DHI:US", "cfd"], "Deutsche Telekom": ["DTED-CHIX", "cfd"], "Gold Miners ETF": ["GDX", "cfd"], "Gold": ["XAUUSD", "cfd"], "Extra Space Storage": ["EXR:US", "cfd"], "Manchester United": ["MANU", "cfd"], "Banco Santander": ["SANE-CHIX", "cfd"], "Abbott Labs": ["ABT:US", "cfd"], "FMC Corporation": ["FMC:US", "cfd"], "Snapchat": ["SNAP", "cfd"], "ThyssenKrupp": ["TKAD-CHIX", "cfd"], "GER 30": ["GERMANY30", "cfd"], "Fortune Brands Home & Security": ["FBHS:US", "cfd"], "Crude Oil Brent": ["UKOUSD", "cfd"], "Coca Cola": ["COKE", "cfd"], "Essex Property Trust": ["ESS:US", "cfd"], "Wm Morrison Supermarkets": ["MRWL-CHIX", "cfd"], "Gilead Sciences": ["GILD:US", "cfd"], "MasterCard": ["MA:US", "cfd"], "Nestl\u00e9": ["NESNZ-CHIX", "cfd"], "CenturyLink": ["CTL:US", "cfd"], "Deutsche Bank": ["DBKD-CHIX", "cfd"], "T-Mobile US, Inc.": ["TMUS", "cfd"], "McDonald's": ["MCDON", "cfd"], "Diamond Offshore Drilling": ["DO:US", "cfd"], "Intel": ["INTEL", "cfd"], "Fifth Third Bank": ["FITB:US", "cfd"], "Best Buy": ["BBY:US", "cfd"], "EQT Corporation": ["EQT:US", "cfd"], "BP PLC": ["BPL-CHIX", "cfd"], "E-Trade": ["ETFC:US", "cfd"], "Stryker": ["SYK:US", "cfd"], "Dow Jones Industrial Average ETF": ["DIA", "cfd"], "NEM \u00d720": ["XEMUSD-L", "crypto"], "Ethereum": ["ETHUSD", "crypto"], "EOS \u00d720": ["EOSUSD-L", "crypto"], "Qtum": ["QTMUSD", "crypto"], "EOS": ["EOSUSD", "crypto"], "Bitcoin Cash \u00d720": ["BCHUSD-L", "crypto"], "Bitcoin": ["BTCUSD", "crypto"], "TRON": ["TRXUSD", "crypto"], "Ripple \u00d720": ["XRPUSD-L", "crypto"], "Stellar \u00d720": ["XLMUSD-L", "crypto"], "Ethereum \u00d750": ["ETHUSD-L", "crypto"], "ZCash": ["ZECUSD", "crypto"], "Litecoin": ["LTCUSD", "crypto"], "Bitcoin Cash": ["BCHUSD", "crypto"], "Bitcoin \u00d7100": ["BTCUSD-L", "crypto"], "OmiseGo": ["OMGUSD", "crypto"], "TRON \u00d750": ["TRXUSD-L", "crypto"], "Cardano \u00d720": ["ADAUSD-L", "crypto"], "Dash": ["DSHUSD", "crypto"], "Litecoin \u00d720": ["LTCUSD-L", "crypto"], "Ripple": ["XRPUSD", "crypto"]}